pyarmor_runtime_000000/__init__.py
pyarmor_runtime_000000/pyarmor_runtime.so
pyarmor_runtime_000000/setup.py
pyarmor_runtime_000000/build/lib/pyarmor_runtime_000000/__init__.py
pyarmor_runtime_000000-1.0.0.dist-info/METADATA
pyarmor_runtime_000000-1.0.0.dist-info/WHEEL
pyarmor_runtime_000000-1.0.0.dist-info/top_level.txt
pyarmor_runtime_000000-1.0.0.dist-info/RECORD
